{"path":{"path":["RIGHT","RIGHT","UP","UP","RIGHT","RIGHT","DOWN","DOWN","RIGHT","DOWN","DOWN","RIGHT","RIGHT","DOWN","DOWN","LEFT","LEFT","DOWN","LEFT","LEFT","UP","UP","LEFT","LEFT","DOWN","DOWN","LEFT","UP","UP","LEFT","LEFT","UP","UP","RIGHT","RIGHT","UP"],"x":2,"y":2,"type":"path_tile"},"saveWorld":{"moveBuildings":[{"X":2,"Y":2,"type":"heros_castle"},{"X":2,"Y":5,"type":"village"},{"X":2,"Y":3,"type":"village"},{"X":7,"Y":3,"type":"village"},{"X":7,"Y":7,"type":"village"},{"X":3,"Y":2,"type":"barracks"},{"X":6,"Y":7,"type":"barracks"},{"X":3,"Y":5,"type":"barracks"},{"X":6,"Y":2,"type":"barracks"},{"X":5,"Y":2,"type":"campfire"},{"X":7,"Y":5,"type":"campfire"},{"X":2,"Y":4,"type":"campfire"},{"X":7,"Y":4,"type":"village"},{"X":9,"Y":4,"type":"barracks"}],"character":{"cards":[{"type":"campfire"},{"type":"campfire"},{"type":"barracks"},{"type":"barracks"},{"type":"village"},{"type":"village"},{"type":"campfire"},{"type":"trap"},{"type":"campfire"}],"equippedWeapon":{"level":10,"x":0,"y":0,"type":"staff"},"equippedHelmet":{"level":9,"x":1,"y":0,"type":"helmet"},"health":99,"cycles":15,"canTakeDamage":true,"experience":35903,"aliveSoldiers":3,"gold":366,"equippedShield":{"level":10,"x":2,"y":0,"type":"shield"},"stats":{"stake":2,"sword":4,"shield":10,"helmet":9,"staff":10,"armour":10},"unequippedItems":[{"type":"strengthpotion"},{"type":"healthpotion"},{"type":"healthpotion"},{"type":"strengthpotion"},{"type":"strengthpotion"},{"type":"healthpotion"}],"bossKills":0,"strengthpotionbuff":0,"position":2,"equippedArmour":{"level":10,"x":3,"y":2,"type":"armour"}},"poop":[{"x":4,"y":5}],"seed":2,"healthPotionsBought":3,"strengthPotionsBought":3,"enemies":[{"index":4,"type":"slug"},{"index":13,"type":"zombie"},{"index":15,"type":"zombie"},{"index":31,"type":"zombie"},{"index":10,"type":"slug"},{"index":22,"type":"slug"},{"index":5,"type":"slug"},{"index":6,"type":"slug"},{"index":7,"type":"slug"}],"cycleBuildings":[{"X":8,"Y":5,"type":"zombiepit"},{"X":1,"Y":4,"type":"zombiepit"},{"X":10,"Y":5,"type":"vampirecastle"},{"X":5,"Y":1,"type":"zombiepit"}],"gameMode":["standard"],"coin":[{"x":0,"y":5}]},"entities":[{"x":2,"y":2,"type":"hero_castle"},{"x":2,"y":5,"type":"village"},{"x":2,"y":3,"type":"village"},{"x":7,"y":3,"type":"village"},{"x":7,"y":7,"type":"village"},{"x":3,"y":2,"type":"barracks"},{"x":6,"y":7,"type":"barracks"},{"x":3,"y":5,"type":"barracks"},{"x":6,"y":2,"type":"barracks"},{"x":8,"y":5,"type":"zombiepit"},{"x":1,"y":4,"type":"zombiepit"},{"x":5,"y":2,"type":"campfire"},{"x":7,"y":5,"type":"campfire"},{"x":2,"y":4,"type":"campfire"},{"x":10,"y":5,"type":"vampirecastle"}],"width":12,"goal-condition":{"goal":"AND","subgoals":[{"goal":"cycles","quantity":40},{"goal":"OR","subgoals":[{"goal":"experience","quantity":10000},{"goal":"AND","subgoals":[{"goal":"bosses"},{"goal":"gold","quantity":100000}]}]}]},"rare_items":["theonering","anduril","treestump","nuke","invinciblepotion"],"height":16}